<annotation>
	<folder>images</folder>
	<filename>00007.jpg</filename>
	<path>E:\STUDYCONTENT\Pycharm\torchcon\images\00007.jpg</path>
	<source>
		<database>Unknown</database>
	</source>
	<size>
		<width>2592</width>
		<height>1944</height>
		<depth>3</depth>
	</size>
	<segmented>0</segmented>
	<object>
		<name>car</name>
		<pose>Unspecified</pose>
		<truncated>0</truncated>
		<difficult>0</difficult>
		<bndbox>
			<xmin>256</xmin>
			<ymin>160</ymin>
			<xmax>2323</xmax>
			<ymax>1519</ymax>
		</bndbox>
	</object>
</annotation>
